simpleapi/__init__.py
simpleapi/templates.py
hexfrost_simpleapi-0.1.7.dist-info/LICENSE
hexfrost_simpleapi-0.1.7.dist-info/METADATA
hexfrost_simpleapi-0.1.7.dist-info/WHEEL
hexfrost_simpleapi-0.1.7.dist-info/RECORD
