Metadata-Version: 2.1
Name: hexfrost-simpleapi
Version: 0.1.7
Summary: Library for simple creating endpoints
Author: Kaziamov
Author-email: kaziamov@outlook.com
Requires-Python: >=3.10,<4.0
Classifier: Programming Language :: Python :: 3
Classifier: Programming Language :: Python :: 3.10
Classifier: Programming Language :: Python :: 3.11
Classifier: Programming Language :: Python :: 3.12
Requires-Dist: fastapi (>=0.70.0)
